hcl2/hcl2.lark
hcl2/hcl2.lark.old
modules/annotations.py
modules/config/__init__.py
modules/config/cloud_config_aws.py
modules/config/cloud_config_azure.py
modules/config/cloud_config_gcp.py
modules/config/resource_handler_configs_aws.py
modules/config/resource_handler_configs_azure.py
modules/config/resource_handler_configs_gcp.py
modules/config_loader.py
modules/drawing.py
modules/fileparser.py
modules/gitlibs.py
modules/graphmaker.py
modules/helpers.py
modules/interpreter.py
modules/provider_detector.py
modules/resource_handlers.py
modules/resource_handlers_aws.py
modules/resource_handlers_azure.py
modules/resource_handlers_gcp.py
modules/resource_transformers.py
modules/tfwrapper.py
override.tf
pyproject.toml
resource_classes/__init__.py
resource_classes/aws/__init__.py
resource_classes/aws/analytics.py
resource_classes/aws/ar.py
resource_classes/aws/blockchain.py
resource_classes/aws/business.py
resource_classes/aws/compute.py
resource_classes/aws/cost.py
resource_classes/aws/database.py
resource_classes/aws/devtools.py
resource_classes/aws/enablement.py
resource_classes/aws/enduser.py
resource_classes/aws/engagement.py
resource_classes/aws/game.py
resource_classes/aws/general.py
resource_classes/aws/groups.py
resource_classes/aws/integration.py
resource_classes/aws/iot.py
resource_classes/aws/management.py
resource_classes/aws/media.py
resource_classes/aws/migration.py
resource_classes/aws/ml.py
resource_classes/aws/mobile.py
resource_classes/aws/network.py
resource_classes/aws/quantum.py
resource_classes/aws/robotics.py
resource_classes/aws/satellite.py
resource_classes/aws/security.py
resource_classes/aws/storage.py
resource_classes/azure/__init__.py
resource_classes/azure/aimachinelearning.py
resource_classes/azure/analytics.py
resource_classes/azure/appservices.py
resource_classes/azure/azureecosystem.py
resource_classes/azure/azurestack.py
resource_classes/azure/blockchain.py
resource_classes/azure/compute.py
resource_classes/azure/containers.py
terravision-0.11.2.dist-info/LICENSE
terravision-0.11.2.dist-info/METADATA
terravision-0.11.2.dist-info/WHEEL
terravision-0.11.2.dist-info/entry_points.txt
terravision-0.11.2.dist-info/RECORD
