Metadata-Version: 2.1
Name: terravision
Version: 0.11.2
Summary: Terraform Architecture Visualizer
License: AGPL-3.0-only
Author: Patrick Chugh
Author-email: terravisionapp@gmail.com
Requires-Python: >=3.11
Classifier: License :: OSI Approved :: GNU Affero General Public License v3
Classifier: Programming Language :: Python :: 3
Classifier: Programming Language :: Python :: 3.11
Classifier: Programming Language :: Python :: 3.12
Requires-Dist: GitPython (==3.1.31)
Requires-Dist: PyYAML (>=6.0)
Requires-Dist: click (==8.1.3)
Requires-Dist: debugpy (>=1.8.0,<2.0.0)
Requires-Dist: graphviz (==0.20.1)
Requires-Dist: graphviz2drawio (>=1.0.0,<2.0.0)
Requires-Dist: ipaddr (>=2.2.0,<3.0.0)
Requires-Dist: ollama (>=0.6.1,<0.7.0)
Requires-Dist: python-hcl2 (==4.3.0)
Requires-Dist: requests (>=2.32.3)
Requires-Dist: tomli (>=2.0.1,<3.0.0)
Requires-Dist: tqdm (==4.65.0)
Requires-Dist: typing-extensions (>=4.0.0,<5.0.0)
